MANIFEST.in
README.rst
setup.py
Optiation.egg-info/PKG-INFO
Optiation.egg-info/SOURCES.txt
Optiation.egg-info/dependency_links.txt
Optiation.egg-info/requires.txt
Optiation.egg-info/top_level.txt
optiation/models.py
optiation/pylog.py