Metadata-Version: 1.1
Name: Optiation
Version: 0.3.6
Summary: A Python package that used to forecast system deployment to Inter-Credit.
Home-page: https://dataxujing.github.io
Author: DataXujing
Author-email: xujing@inter-credit.net
License: Apache License, Version 2.0
Platform: linux/Windows
Classifier: Development Status :: 3 - Alpha
Classifier: Topic :: Text Processing
Classifier: License :: OSI Approved :: MIT License
Classifier: Programming Language :: Python :: 2
Classifier: Programming Language :: Python :: 2.7
Classifier: Programming Language :: Python :: 3
Classifier: Programming Language :: Python :: 3.6
